gsa_pca/__init__.py
gsa_pca/main.py
gsa_pca-0.1.0.dist-info/METADATA
gsa_pca-0.1.0.dist-info/WHEEL
gsa_pca-0.1.0.dist-info/RECORD
